{
    "uuid": [
        {
            "value": "033523f0-a889-4fcf-9af9-7c1cbc91b2a1"
        }
    ],
    "langcode": [
        {
            "value": "en"
        }
    ],
    "type": [
        {
            "target_id": "recipe",
            "target_type": "node_type",
            "target_uuid": "79ef0e05-2b8d-4895-8570-6209f5b52ab2"
        }
    ],
    "revision_timestamp": [
        {
            "value": "2018-07-01T15:11:20+00:00",
            "format": "Y-m-d\\TH:i:sP"
        }
    ],
    "revision_uid": [
        {
            "target_type": "user",
            "target_uuid": "ab7d90de-645b-48fb-b10f-fd74894d87b4"
        }
    ],
    "revision_log": [],
    "status": [
        {
            "value": true
        }
    ],
    "title": [
        {
            "value": "Victoria sponge cake"
        }
    ],
    "uid": [
        {
            "target_type": "user",
            "target_uuid": "ab7d90de-645b-48fb-b10f-fd74894d87b4"
        }
    ],
    "created": [
        {
            "value": "2018-07-01T15:11:20+00:00",
            "format": "Y-m-d\\TH:i:sP"
        }
    ],
    "changed": [
        {
            "value": "2018-07-01T15:11:20+00:00",
            "format": "Y-m-d\\TH:i:sP"
        }
    ],
    "promote": [
        {
            "value": true
        }
    ],
    "sticky": [
        {
            "value": false
        }
    ],
    "default_langcode": [
        {
            "value": true
        }
    ],
    "revision_translation_affected": [
        {
            "value": true
        }
    ],
    "path": [
        {
            "alias": "\/recipes\/victoria-sponge-cake",
            "pid": 31,
            "langcode": "en"
        }
    ],
    "field_author": [
        {
            "target_type": "user",
            "target_uuid": "ab7d90de-645b-48fb-b10f-fd74894d87b4"
        }
    ],
    "field_cooking_time": [
        {
            "value": 20
        }
    ],
    "field_difficulty": [
        {
            "value": "easy"
        }
    ],
    "field_image": [
        {
            "alt": "A classic, uncut Victoria sponge with a deep filling of butter cream and jam",
            "title": null,
            "width": 768,
            "height": 512,
            "target_type": "file",
            "target_uuid": "e6d1b388-4a14-4292-bca0-de0bc4377945"
        }
    ],
    "field_ingredients": [
        {
            "value": "225g butter or margarine"
        },
        {
            "value": "225g caster sugar"
        },
        {
            "value": "225g self-raising flour"
        },
        {
            "value": "4 eggs"
        },
        {
            "value": "1 tsp baking powder"
        },
        {
            "value": "3 tbsp of jam for the filling"
        },
        {
            "value": "Icing sugar to dust the top"
        },
        {
            "value": "Cream to serve"
        }
    ],
    "field_number_of_servings": [
        {
            "value": 10
        }
    ],
    "field_preparation_time": [
        {
            "value": 20
        }
    ],
    "field_recipe_category": [
        {
            "target_type": "taxonomy_term",
            "target_uuid": "4bb6b55e-474d-4bb7-9739-b12f8bf31358"
        }
    ],
    "field_recipe_instruction": [
        {
            "value": "<ol>\n  <li>Preheat the oven to 350\u00b0F\/180\u00b0C and grease two 8 inch cake tins.<\/li>\n  <li>In a large bowl, mix the butter and sugar together, then add the eggs, flour and baking powder.<\/li>\n  <li>Spread the mix evenly between the 2 cake tins.<\/li>\n  <li>Place both tins in the middle of the preheated oven for 20 minutes, before checking with a knife. When the knife comes out clean, it's ready!<\/li>\n  <li>Allow to cool in the tins before moving them onto a cooling rack.<\/li>\n  <li>Add the jam, stack, dust with icing sugar and serve with a big dollop of cream. Enjoy!<\/li>\n<\/ol>\n",
            "format": "basic_html"
        }
    ],
    "field_summary": [
        {
            "value": "A traditional Victoria sponge cake, perfect for any afternoon with a cup of tea.",
            "format": "basic_html"
        }
    ],
    "field_tags": [
        {
            "target_type": "taxonomy_term",
            "target_uuid": "d1ed1a35-6153-49e1-91bf-a622f8f1f000"
        }
    ]
}